setup.py
awschimp/__init__.py
awschimp/awscreds.py
awschimp.egg-info/PKG-INFO
awschimp.egg-info/SOURCES.txt
awschimp.egg-info/dependency_links.txt
awschimp.egg-info/not-zip-safe
awschimp.egg-info/requires.txt
awschimp.egg-info/top_level.txt