Metadata-Version: 1.0
Name: awschimp
Version: 0.0.2
Summary: aws utils fit for a chimp
Home-page: https://github.com/mschurenko/awschimp
Author: Matt Schurenko
Author-email: matt.schurenko@gmail.com
License: MIT
Keywords: aws,sts,boto,profile,awschimp
Platform: UNKNOWN
